.coveragerc
.mypy.ini
.pylintrc
CHANGES.rst
LICENSE.txt
MANIFEST.in
README.rst
local.py
setup.cfg
setup.py
tox.ini
sysca/__init__.py
sysca/api.py
sysca/autogen.py
sysca/certinfo.py
sysca/compat.py
sysca/crlinfo.py
sysca/exceptions.py
sysca/files.py
sysca/formats.py
sysca/keys.py
sysca/objects.py
sysca/py.typed
sysca/ssh.py
sysca/tool.py
sysca.egg-info/PKG-INFO
sysca.egg-info/SOURCES.txt
sysca.egg-info/dependency_links.txt
sysca.egg-info/entry_points.txt
sysca.egg-info/requires.txt
sysca.egg-info/top_level.txt
sysca.egg-info/zip-safe
tests/helpers.py
tests/test_autogen.py
tests/test_crl.py
tests/test_formats.py
tests/test_keys.py
tests/test_sysca.py
tests/test_tool.py
tests/files/dsa.key
tests/files/dsa.pub
tests/files/ec-p256-ca.crl
tests/files/ec-p256-ca.crl.out
tests/files/ec-p256-ca.crt
tests/files/ec-p256-ca.crt.out
tests/files/ec-p256-ca.csr
tests/files/ec-p256-ca.csr.out
tests/files/ec-p256.key
tests/files/ec-p256.psw.key
tests/files/ec-p256.pub
tests/files/ec2-rich.crt
tests/files/ec2-rich.crt.out
tests/files/ec2-rich.csr
tests/files/ec2-rich.csr.out
tests/files/ec2.key
tests/files/ec2.pub
tests/files/ed25519.key
tests/files/ed25519.pub
tests/files/ed448.key
tests/files/ed448.pub
tests/files/gen.sh
tests/files/letsencrypt-org.crt
tests/files/letsencrypt-org.crt.out
tests/files/letsencrypt-x3.crt
tests/files/letsencrypt-x3.crt.out
tests/files/password.txt
tests/files/rsa1.key
tests/files/rsa1.pub
tests/files/ssh/certs.sh
tests/files/ssh/gen.sh
tests/files/ssh/new-dsa-nopsw.key
tests/files/ssh/new-dsa-nopsw.key-cert.pub
tests/files/ssh/new-dsa-nopsw.key.pub
tests/files/ssh/new-dsa-psw.key
tests/files/ssh/new-dsa-psw.key.pub
tests/files/ssh/new-ecdsa-nopsw.key
tests/files/ssh/new-ecdsa-nopsw.key-cert.pub
tests/files/ssh/new-ecdsa-nopsw.key.pub
tests/files/ssh/new-ecdsa-psw.key
tests/files/ssh/new-ecdsa-psw.key.pub
tests/files/ssh/new-ed25519-nopsw.key
tests/files/ssh/new-ed25519-nopsw.key-cert.pub
tests/files/ssh/new-ed25519-nopsw.key.pub
tests/files/ssh/new-ed25519-psw.key
tests/files/ssh/new-ed25519-psw.key.pub
tests/files/ssh/new-rsa-nopsw.key
tests/files/ssh/new-rsa-nopsw.key-cert.pub
tests/files/ssh/new-rsa-nopsw.key.pub
tests/files/ssh/new-rsa-psw.key
