Metadata-Version: 2.1
Name: sysca
Version: 2.3
Summary: Certificate tool for Sysadmins
Home-page: https://github.com/markokr/sysca
Author: Marko Kreen
Author-email: markokr@gmail.com
License: ISC
Keywords: x509,tls,ssl,certificate,authority,command-line,server,authentication
Classifier: Development Status :: 5 - Production/Stable
Classifier: Intended Audience :: System Administrators
Classifier: License :: OSI Approved :: ISC License (ISCL)
Classifier: Operating System :: OS Independent
Classifier: Programming Language :: Python :: 3
Classifier: Topic :: Security :: Cryptography
Classifier: Topic :: System :: Systems Administration
Classifier: Topic :: Utilities
License-File: LICENSE.txt
